odoo/addons/ddmrp_packaging/README.rst
odoo/addons/ddmrp_packaging/__init__.py
odoo/addons/ddmrp_packaging/__manifest__.py
odoo/addons/ddmrp_packaging/i18n/ddmrp_packaging.pot
odoo/addons/ddmrp_packaging/i18n/es.po
odoo/addons/ddmrp_packaging/i18n/it.po
odoo/addons/ddmrp_packaging/i18n/pt_BR.po
odoo/addons/ddmrp_packaging/models/__init__.py
odoo/addons/ddmrp_packaging/models/stock_buffer.py
odoo/addons/ddmrp_packaging/readme/CONTRIBUTORS.md
odoo/addons/ddmrp_packaging/readme/DESCRIPTION.md
odoo/addons/ddmrp_packaging/readme/HISTORY.md
odoo/addons/ddmrp_packaging/readme/INSTALL.md
odoo/addons/ddmrp_packaging/static/description/icon.png
odoo/addons/ddmrp_packaging/static/description/index.html
odoo/addons/ddmrp_packaging/tests/__init__.py
odoo/addons/ddmrp_packaging/tests/test_ddmrp_packaging.py
odoo/addons/ddmrp_packaging/views/stock_buffer_view.xml
odoo/addons/ddmrp_packaging/wizards/__init__.py
odoo/addons/ddmrp_packaging/wizards/make_procurement_buffer.py
odoo/addons/ddmrp_packaging/wizards/make_procurement_buffer_view.xml
odoo_addon_ddmrp_packaging-18.0.1.0.0.2.dist-info/METADATA
odoo_addon_ddmrp_packaging-18.0.1.0.0.2.dist-info/WHEEL
odoo_addon_ddmrp_packaging-18.0.1.0.0.2.dist-info/top_level.txt
odoo_addon_ddmrp_packaging-18.0.1.0.0.2.dist-info/RECORD
